yaml_models/__init__.py
yaml_models/config.py
yaml_models/model.py
yaml_models-0.1.0.dist-info/LICENSE
yaml_models-0.1.0.dist-info/METADATA
yaml_models-0.1.0.dist-info/WHEEL
yaml_models-0.1.0.dist-info/top_level.txt
yaml_models-0.1.0.dist-info/RECORD
