Metadata-Version: 2.1
Name: yaml-models
Version: 0.1.0
Summary: Generate torch models from yaml config files.
Home-page: https://github.com/tomrtk/yaml-models
Author: Tom-R. T. Kvalvaag
License: MIT
Platform: UNKNOWN
Classifier: License :: OSI Approved :: MIT License
Classifier: Programming Language :: Python :: 3
Classifier: Programming Language :: Python :: 3 :: Only
Classifier: Programming Language :: Python :: 3.7
Classifier: Programming Language :: Python :: 3.8
Classifier: Programming Language :: Python :: 3.9
Classifier: Programming Language :: Python :: 3.10
Requires-Python: >=3.7
License-File: LICENSE
Requires-Dist: numpy (>=1.21.5)
Requires-Dist: pyyaml (>=6.0)
Requires-Dist: torch (>=1.10.0)
Provides-Extra: dev
Requires-Dist: autopep8 ; extra == 'dev'
Requires-Dist: build ; extra == 'dev'
Requires-Dist: flake8 ; extra == 'dev'
Requires-Dist: isort ; extra == 'dev'
Requires-Dist: mypy (>=0.902) ; extra == 'dev'
Requires-Dist: pre-commit ; extra == 'dev'
Requires-Dist: pyupgrade ; extra == 'dev'
Requires-Dist: tox ; extra == 'dev'
Requires-Dist: twine ; extra == 'dev'
Requires-Dist: types-all ; extra == 'dev'
Provides-Extra: testing
Requires-Dist: covdefaults ; extra == 'testing'
Requires-Dist: coverage ; extra == 'testing'
Requires-Dist: pytest (>=4.0.0) ; extra == 'testing'
